COPYING
MANIFEST.in
README
health_archives_view.xml
setup.py
./__init__.py
./health_archives.py
./health_archives_view.xml
./tryton.cfg
./doc/index.rst
./icons/archives.svg
./locale/ar.po
./locale/de.po
./locale/el.po
./locale/es.po
./locale/fr.po
./locale/it_IT.po
./locale/ja_JP.po
./locale/lo.po
./locale/pt_BR.po
./locale/zh_CN.po
./tests/__init__.py
./tests/test_health_archives.py
./view/gnuhealth_paper_archive_form.xml
./view/gnuhealth_paper_archive_tree.xml
icons/README
icons/archives.svg
locale/ar.po
locale/de.po
locale/el.po
locale/es.po
locale/fr.po
locale/it_IT.po
locale/ja_JP.po
locale/lo.po
locale/pt_BR.po
locale/zh_CN.po
trytond_health_archives.egg-info/PKG-INFO
trytond_health_archives.egg-info/SOURCES.txt
trytond_health_archives.egg-info/dependency_links.txt
trytond_health_archives.egg-info/entry_points.txt
trytond_health_archives.egg-info/not-zip-safe
trytond_health_archives.egg-info/requires.txt
trytond_health_archives.egg-info/top_level.txt
view/gnuhealth_paper_archive_form.xml
view/gnuhealth_paper_archive_tree.xml